hypothesis_drf/__init__.py
hypothesis_drf-1.0.0.dist-info/DESCRIPTION.rst
hypothesis_drf-1.0.0.dist-info/METADATA
hypothesis_drf-1.0.0.dist-info/RECORD
hypothesis_drf-1.0.0.dist-info/WHEEL
hypothesis_drf-1.0.0.dist-info/metadata.json
hypothesis_drf-1.0.0.dist-info/top_level.txt
