Metadata-Version: 2.0
Name: hypothesis-drf
Version: 1.0.0
Summary: Hypothesis DRF
Home-page: https://gitlab.com/schmidt.simon/hypothesis-drf
Author: Simon Schmidt
Author-email: schmidt.simon@gmail.com
License: MPL v2
Platform: UNKNOWN
Classifier: Topic :: Software Development :: Testing
Classifier: Intended Audience :: Developers
Classifier: License :: OSI Approved :: Mozilla Public License 2.0 (MPL 2.0)
Requires-Dist: hypothesis[fakefactory] (<4,>=3.27)
Requires-Dist: hypothesis-fspaths
Requires-Dist: djangorestframework (<4,>=3.6)
Provides-Extra: tests
Requires-Dist: pytest (~=3.2); extra == 'tests'
Requires-Dist: pytest-django (~=3.1); extra == 'tests'
Requires-Dist: Django (<2); extra == 'tests'
Requires-Dist: flake8 (<4); extra == 'tests'
